Metadata-Version: 1.0
Name: bingau-distributions
Version: 1.0
Summary: Gaussian and Binomial distributions
Home-page: UNKNOWN
Author: Fuhua Liu
Author-email: liufuhua301@126.com
License: UNKNOWN
Platform: UNKNOWN
